{
  "name": "Wizard of Oz",
  "type": "characters",
  "rarity": "legendary",
  "images": [
    {
      "url": "https://onceuponagalaxy.wiki.gg/images/0/02/Character_Wizard_of_Oz.png?2195dd&format=original",
      "type": "art"
    },
    {
      "url": "https://onceuponagalaxy.wiki.gg/images/5/56/Character_Wizard_of_Oz_Card_Bronze.png?format=original",
      "type": "bronze",
      "original": "original/wizard-of-oz_unknown_0.png",
      "converted": "converted/wizard-of-oz_unknown_0.webp"
    },
    {
      "url": "https://onceuponagalaxy.wiki.gg/images/8/8c/Character_Wizard_of_Oz_Card_Silver.png?format=original",
      "type": "silver"
    },
    {
      "url": "https://onceuponagalaxy.wiki.gg/images/1/11/Character_Wizard_of_Oz_Card_Gold.png?format=original",
      "type": "gold",
      "original": "original/wizard-of-oz_unknown_1.png",
      "converted": "converted/wizard-of-oz_unknown_1.webp"
    }
  ],
  "traits": [
    "Mage",
    "Villain"
  ],
  "abilities": [
    {
      "type": "Support",
      "description": "(X) (+2/+2 for each spell you've cast this game.)",
      "gold_description": "(X) (+4/+4 for each spell you've cast this game.)"
    }
  ],
  "attack": 3,
  "health": 3,
  "deck_type": "Shared"
}